CHANGELOG.rst
LICENSE
MANIFEST.in
README.rst
setup.py
./CHANGELOG.rst
./README.rst
./ROADMAP.rst
./design/punchline_icon_design-512x512.svg
./design/punchline_logo_design-512x512.svg
./turberfield/punchline/default.cfg
./turberfield/punchline/assets/punchline_icon-512x512.svg
./turberfield/punchline/assets/punchline_logo-512x512.svg
./turberfield/punchline/doc/changes.rst
./turberfield/punchline/doc/dialogue.rst
./turberfield/punchline/doc/index.rst
./turberfield/punchline/doc/install.rst
./turberfield/punchline/doc/intro.rst
./turberfield/punchline/doc/roadmap.rst
./turberfield/punchline/doc/themes.rst
./turberfield/punchline/doc/widgets.rst
./turberfield/punchline/doc/html/_static/basic.css
./turberfield/punchline/doc/html/_static/pygments.css
./turberfield/punchline/doc/html/_static/css/badge_only.css
./turberfield/punchline/doc/html/_static/css/theme.css
./turberfield/punchline/doc/html/_static/css/fonts/Roboto-Slab-Bold.woff
./turberfield/punchline/doc/html/_static/css/fonts/Roboto-Slab-Bold.woff2
./turberfield/punchline/doc/html/_static/css/fonts/Roboto-Slab-Regular.woff
./turberfield/punchline/doc/html/_static/css/fonts/Roboto-Slab-Regular.woff2
./turberfield/punchline/doc/html/_static/css/fonts/fontawesome-webfont.svg
./turberfield/punchline/doc/html/_static/css/fonts/fontawesome-webfont.woff
./turberfield/punchline/doc/html/_static/css/fonts/fontawesome-webfont.woff2
./turberfield/punchline/doc/html/_static/css/fonts/lato-bold-italic.woff
./turberfield/punchline/doc/html/_static/css/fonts/lato-bold-italic.woff2
./turberfield/punchline/doc/html/_static/css/fonts/lato-bold.woff
./turberfield/punchline/doc/html/_static/css/fonts/lato-bold.woff2
./turberfield/punchline/doc/html/_static/css/fonts/lato-normal-italic.woff
./turberfield/punchline/doc/html/_static/css/fonts/lato-normal-italic.woff2
./turberfield/punchline/doc/html/_static/css/fonts/lato-normal.woff
./turberfield/punchline/doc/html/_static/css/fonts/lato-normal.woff2
turberfield_punchline.egg-info/PKG-INFO
turberfield_punchline.egg-info/SOURCES.txt
turberfield_punchline.egg-info/dependency_links.txt
turberfield_punchline.egg-info/entry_points.txt
turberfield_punchline.egg-info/namespace_packages.txt
turberfield_punchline.egg-info/not-zip-safe
turberfield_punchline.egg-info/requires.txt
turberfield_punchline.egg-info/top_level.txt