Metadata-Version: 1.1
Name: turberfield-punchline
Version: 0.8.0
Summary: A static blog engine with great comedy timing.
Home-page: https://github.com/tundish/turberfield-punchline/issues
Author: D Haynes
Author-email: tundish@gigeconomy.org.uk
License: UNKNOWN
Platform: UNKNOWN
Classifier: Operating System :: POSIX
Classifier: Programming Language :: Python :: 3.8
Classifier: License :: OSI Approved :: GNU General Public License v3 or later (GPLv3+)
